{"warezcdn":{"imdb":"tt0111897","name":"Blue Seed","href":"https://embed.warezcdn.net/serie/tt0111897","title":"Blue Seed"},"imdb":{"id":"tt0111897","review_api_path":"/reviews/tt0111897","imdb":"https://www.imdb.com/title/tt0111897","contentType":"TVSeries","productionStatus":"Released","title":"Blue Seed","image":"https://m.media-amazon.com/images/M/MV5BZDZjZDllMjEtM2RjOS00MDEwLWI1NzktMGZhZGM2ZmZkNjExXkEyXkFqcGdeQXVyOTA0MzY4MjY@._V1_.jpg","images":["https://m.media-amazon.com/images/M/MV5BMjA2OTY0ODU4MF5BMl5BanBnXkFtZTYwMzM2OTc4._V1_.jpg","https://m.media-amazon.com/images/M/MV5BMTA4OTIzNDEzNzBeQTJeQWpwZ15BbWU2MDAzNzk3OA@@._V1_.jpg","https://m.media-amazon.com/images/M/MV5BMTI5NTY4NzY4MV5BMl5BanBnXkFtZTYwMDk1Mjg4._V1_.jpg","https://m.media-amazon.com/images/M/MV5BMTkxODU2MzMxNl5BMl5BanBnXkFtZTYwMTcwODg4._V1_.jpg","https://m.media-amazon.com/images/M/MV5BMTY3MDUyNDE5NV5BMl5BanBnXkFtZTYwNTcwODg4._V1_.jpg","https://m.media-amazon.com/images/M/MV5BMTIxODAwMDUzOV5BMl5BanBnXkFtZTYwNjM3MDk4._V1_.jpg","https://m.media-amazon.com/images/M/MV5BMjEzNjIyNDAwM15BMl5BanBnXkFtZTYwNDI1Mzk4._V1_.jpg","https://m.media-amazon.com/images/M/MV5BMjExMDkyMTA1NV5BMl5BanBnXkFtZTYwMjE3Mzk4._V1_.jpg","https://m.media-amazon.com/images/M/MV5BODg2Mzc2NDQ0OV5BMl5BanBnXkFtZTYwMDQyNTk4._V1_.jpg","https://m.media-amazon.com/images/M/MV5BMjQ3MTA5ODk1MF5BMl5BanBnXkFtZTYwNTc4MDA5._V1_.jpg","https://m.media-amazon.com/images/M/MV5BOTMxNjkyMzQxMF5BMl5BanBnXkFtZTYwNjM1MzA5._V1_.jpg","https://m.media-amazon.com/images/M/MV5BMTQ4MDA5OTQ4N15BMl5BanBnXkFtZTYwOTcyNjA5._V1_.jpg","https://m.media-amazon.com/images/M/MV5BMTcxNzUwMjczMl5BMl5BanBnXkFtZTYwMjkzOTA5._V1_.jpg"],"plot":"A young girl must fulfill her destiny as a foretold demon fighter with help from a cursed boy and a special investigations team.","rating":{"count":307,"star":6.9},"award":{"wins":0,"nominations":0},"contentRating":"TV-14","genre":"Animation,Action,Adventure","year":1994,"runtime":null,"releaseDeatiled":{"day":5,"month":10,"year":1994,"releaseLocation":{"country":"Japan","cca2":"JP"},"originLocations":[{"country":"Japan","cca2":"JP"}]},"spokenLanguages":[{"language":"English","id":"en"},{"language":"Japanese","id":"ja"}],"filmingLocations":[],"actors":["Matt Greenfield","Akio Ôtsuka","Jôji Nakata"],"directors":[],"top_credits":[{"name":"Stars","value":["Matt Greenfield","Akio Ôtsuka","Jôji Nakata"]}],"seasons":[{"id":"1","name":"Season 1","episodes":[{"idx":1,"no":"S1, Ep1","title":"Kushinadahime","image":"https://m.media-amazon.com/images/G/01/IMDb/spinning-progress.gif","image_large":"https://m.media-amazon.com/images/G/01/IMDb/spinning-progress.gif","plot":"Momiji finds out she isn't as normal as she thought when she discovers she's the Kushinada.","publishedDate":"5 Oct. 1994","rating":{"count":9,"star":7.1}},{"idx":3,"no":"S1, Ep3","title":"Haru desu! Shuto desu! Ganbaranakucha!!","image":"https://m.media-amazon.com/images/G/01/IMDb/spinning-progress.gif","image_large":"https://m.media-amazon.com/images/G/01/IMDb/spinning-progress.gif","plot":"The TAC bring Momiji to Tokyo for her protection but it isn't as safe as everyone thought.","publishedDate":"19 Oct. 1994","rating":{"count":0,"star":0}},{"idx":6,"no":"S1, Ep6","title":"Fukuzatsu! Nankai! Otoko wa tsurai ne?!","image":"https://m.media-amazon.com/images/G/01/IMDb/spinning-progress.gif","image_large":"https://m.media-amazon.com/images/G/01/IMDb/spinning-progress.gif","plot":"Yaegashi worries he isn't pulling his weight with the TAC and hopes to prove himself with some new tech.","publishedDate":"9 Nov. 1994","rating":{"count":0,"star":0}},{"idx":8,"no":"S1, Ep8","title":"Nan nano! Hen nano! Raibaru tôjô?!","image":"https://m.media-amazon.com/images/G/01/IMDb/spinning-progress.gif","image_large":"https://m.media-amazon.com/images/G/01/IMDb/spinning-progress.gif","plot":"A priestess names Yamazaki appears who considered Momiji her rival and challenges her.","publishedDate":"23 Nov. 1994","rating":{"count":0,"star":0}},{"idx":11,"no":"S1, Ep11","title":"Yakimoki Yakimochi?! Anbirîbabô!!","image":"https://m.media-amazon.com/images/G/01/IMDb/spinning-progress.gif","image_large":"https://m.media-amazon.com/images/G/01/IMDb/spinning-progress.gif","plot":"Yamazaki not only transfers to Momiji's class, she's also spending time with Kusanagi!","publishedDate":"14 Dec. 1994","rating":{"count":0,"star":0}},{"idx":12,"no":"S1, Ep12","title":"Kanjiru?! Ki ni naru! Hakyoku no yokan!!","image":"https://m.media-amazon.com/images/G/01/IMDb/spinning-progress.gif","image_large":"https://m.media-amazon.com/images/G/01/IMDb/spinning-progress.gif","plot":"An Aragami is leaving its skin on buildings while Momiji and Kusanagi are both having a hard time.","publishedDate":"21 Dec. 1994","rating":{"count":0,"star":0}},{"idx":14,"no":"S1, Ep14","title":"Oimasu! Yamato-ji! Koi no midareuchi!!","image":"https://m.media-amazon.com/images/G/01/IMDb/spinning-progress.gif","image_large":"https://m.media-amazon.com/images/G/01/IMDb/spinning-progress.gif","plot":"The return of Kaede and Susano-oh cause confusion while new Aragami begin to pollute Nara with pollen.","publishedDate":"4 Jan. 1995","rating":{"count":0,"star":0}},{"idx":16,"no":"S1, Ep16","title":"Yamato yo mahoroba, nageki no wakasa","image":"https://m.media-amazon.com/images/G/01/IMDb/spinning-progress.gif","image_large":"https://m.media-amazon.com/images/G/01/IMDb/spinning-progress.gif","plot":"Kunikida investigates the death of a friend he hasn't seen for years while a local ghost story plays out.","publishedDate":"18 Jan. 1995","rating":{"count":0,"star":0}},{"idx":20,"no":"S1, Ep20","title":"Tadaima! Furusato! Kibô no joshô!!","image":"https://m.media-amazon.com/images/G/01/IMDb/spinning-progress.gif","image_large":"https://m.media-amazon.com/images/G/01/IMDb/spinning-progress.gif","plot":"Momiji returns home to Izumo and Kusanagi battles for his life against Susano-oh.","publishedDate":"15 Feb. 1995","rating":{"count":0,"star":0}},{"idx":21,"no":"S1, Ep21","title":"Sayonara? Iya desu! Namida no wakare?!","image":"https://m.media-amazon.com/images/G/01/IMDb/spinning-progress.gif","image_large":"https://m.media-amazon.com/images/G/01/IMDb/spinning-progress.gif","plot":"Momiji and Kaede's mother faces Kaede and Kusanagi's fight comes to a bitter end.","publishedDate":"22 Feb. 1995","rating":{"count":0,"star":0}},{"idx":23,"no":"S1, Ep23","title":"Saikai tabidachi watashi makenai!","image":"https://m.media-amazon.com/images/G/01/IMDb/spinning-progress.gif","image_large":"https://m.media-amazon.com/images/G/01/IMDb/spinning-progress.gif","plot":"While hiding from the government, Murakumo kidnaps Momiji, hoping to use her as a bargaining chip against Kaede.","publishedDate":"8 Mar. 1995","rating":{"count":0,"star":0}}]}],"href":"https://m.media-amazon.com/images/M/MV5BZDZjZDllMjEtM2RjOS00MDEwLWI1NzktMGZhZGM2ZmZkNjExXkEyXkFqcGdeQXVyOTA0MzY4MjY@._V1_.jpg","aired":"5/10/1994","rating_star":6.9,"rating_count":307,"staff":"","duration":""}}