{"warezcdn":{"imdb":"tt13004300","name":"Null & Peta","href":"https://embed.warezcdn.net/serie/tt13004300","title":"Null & Peta"},"imdb":{"id":"tt13004300","review_api_path":"/reviews/tt13004300","imdb":"https://www.imdb.com/title/tt13004300","contentType":"TVSeries","productionStatus":"Released","title":"Null & Peta","images":[],"plot":"","rating":{"count":19,"star":6.1},"award":{"wins":0,"nominations":0},"genre":"Comedy,Sci-Fi","year":2019,"runtime":null,"releaseDeatiled":{"day":4,"month":10,"year":2019,"releaseLocation":{"country":"Japan","cca2":"JP"},"originLocations":[{"country":"Japan","cca2":"JP"}]},"spokenLanguages":[{"language":"Japanese","id":"ja"}],"filmingLocations":[],"actors":["Reina Ueda","Azumi Waki"],"directors":[],"top_credits":[],"seasons":[],"aired":"4/10/2019","rating_star":6.1,"rating_count":19,"staff":"","duration":""}}